vikitext/__main__.py
vikitext/article_links.py
vikitext/get_text.py
vikitext/hyperlinks.py
vikitext/data/filter_links_vikidia.txt
vikitext/data/vikidia_source.txt
vikitext-0.0.4.dist-info/LICENCE.txt
vikitext-0.0.4.dist-info/METADATA
vikitext-0.0.4.dist-info/WHEEL
vikitext-0.0.4.dist-info/top_level.txt
vikitext-0.0.4.dist-info/RECORD
