Metadata-Version: 2.1
Name: vikitext
Version: 0.0.4
Summary: Retrieve article links and text from Vikidia and their equivalents in Wikipedia
Home-page: https://github.com/CristinaGHolgado/vikitext
Author: Cristina Garcia Holgado
Author-email: cristina.garcia-holgado@etu.unistra.fr
License: MIT
Keywords: corpus,vikidia,wikicommons,wikipedia
Platform: UNKNOWN
Classifier: Programming Language :: Python :: 3
Classifier: Operating System :: Microsoft :: Windows
Requires-Python: >=3.6
Requires-Dist: beautifulsoup4
Requires-Dist: requests
Requires-Dist: numpy
Requires-Dist: pandas
